pyrand48/__init__.py
pyrand48/rand48.py
pyrand48-0.1.9.dist-info/WHEEL
pyrand48-0.1.9.dist-info/METADATA
pyrand48-0.1.9.dist-info/RECORD
