Metadata-Version: 2.4
Name: pyrand48
Version: 0.1.9
Summary: An implementation of the rand48 linear congruential generator.
Author: MLE Slone
Author-email: MLE Slone <m.slone@gmail.com>
License-Expression: MIT
Classifier: Programming Language :: Python :: 3
Classifier: Programming Language :: Python :: 3.12
Classifier: Programming Language :: Python :: 3.13
Classifier: Programming Language :: Python :: 3.14
Requires-Python: >=3.12, <4
Project-URL: Repository, https://github.com/uklibraries/pyrand48/
